SyMBac/PSF.py
SyMBac/__init__.py
SyMBac/cell.py
SyMBac/cell_geometry.py
SyMBac/cell_simulation.py
SyMBac/colony_renderer.py
SyMBac/colony_simulation.py
SyMBac/drawing.py
SyMBac/misc.py
SyMBac/pySHINE.py
SyMBac/renderer.py
SyMBac/simulation.py
SyMBac/trench_geometry.py
SyMBac/external/__init__.py
SyMBac/external/DeLTA/LICENSE
SyMBac/external/DeLTA/README.md
SyMBac/external/DeLTA/__init__.py
SyMBac/external/DeLTA/all_mother_props_1.pickle
SyMBac/external/DeLTA/all_mother_props_2.pickle
SyMBac/external/DeLTA/bioformats2sequence.py
SyMBac/external/DeLTA/bioformats_env.yml
SyMBac/external/DeLTA/config.py
SyMBac/external/DeLTA/data.py
SyMBac/external/DeLTA/data_structure.txt
SyMBac/external/DeLTA/delta_env.yml
SyMBac/external/DeLTA/model.py
SyMBac/external/DeLTA/pipeline.py
SyMBac/external/DeLTA/segmentation.py
SyMBac/external/DeLTA/segmentation_chambers.py
SyMBac/external/DeLTA/tracking.py
SyMBac/external/DeLTA/train_seg.py
SyMBac/external/DeLTA/train_seg_chambers.py
SyMBac/external/DeLTA/train_track.py
SyMBac/external/DeLTA/utilities.py
SyMBac/sample_images/__init__.py
SyMBac/sample_images/sample_100x.tiff
SyMBac/sample_images/sample_100x_stationary.tiff
SyMBac/sample_images/sample_DeLTA.tiff
SyMBac-0.4.0.dist-info/LICENSE
SyMBac-0.4.0.dist-info/METADATA
SyMBac-0.4.0.dist-info/WHEEL
SyMBac-0.4.0.dist-info/top_level.txt
SyMBac-0.4.0.dist-info/RECORD
