Metadata-Version: 2.1
Name: SyMBac
Version: 0.4.0
Summary: A package for generating synthetic images of bactera in phase contrast or fluorescence. Used for creating training data for machine learning segmentation and tracking algorithms.
Home-page: https://github.com/georgeoshardo/SyMBac
Author: Georgeos Hardo
Author-email: gh464@cam.ac.uk
License: GPL-2.0
Classifier: Development Status :: 3 - Alpha
Classifier: Intended Audience :: Science/Research
Classifier: License :: OSI Approved :: GNU General Public License v2 (GPLv2)
Classifier: Operating System :: POSIX :: Linux
Classifier: Operating System :: MacOS :: MacOS X
Classifier: Operating System :: Microsoft :: Windows
Classifier: Programming Language :: Python :: 3.8
Classifier: Programming Language :: Python :: 3.9
Classifier: Programming Language :: Python :: 3.10
Classifier: Topic :: Scientific/Engineering :: Bio-Informatics
Classifier: Topic :: Scientific/Engineering :: Image Processing
Classifier: Topic :: Scientific/Engineering
License-File: LICENSE
Requires-Dist: tifffile
Requires-Dist: scikit-image
Requires-Dist: matplotlib
Requires-Dist: tqdm
Requires-Dist: pandas
Requires-Dist: natsort
Requires-Dist: jupyterlab
Requires-Dist: ipywidgets
Requires-Dist: joblib
Requires-Dist: scipy
Requires-Dist: napari[all]
Requires-Dist: pymunk
Requires-Dist: pyglet
Requires-Dist: matplotlib-scalebar
Requires-Dist: psfmodels
Requires-Dist: sphinx-automodapi
Requires-Dist: sphinx-autobuild
Requires-Dist: nbsphinx
Requires-Dist: sphinx-copybutton
Requires-Dist: sphinx-rtd-theme
Requires-Dist: pandoc
Requires-Dist: zarr
